cognitive_sdk/__init__.py
cognitive_sdk/core/__init__.py
cognitive_sdk/core/metadata_responder.py
cognitive_sdk/core/orcustrator.py
cognitive_sdk/core/proxy.py
cognitive_sdk/core/publisher.py
cognitive_sdk/core/subscriber.py
cognitive_sdk/core/subscriber_manager.py
cognitive_sdk/devices/__init__.py
cognitive_sdk/devices/device.py
cognitive_sdk/devices/device_manager.py
cognitive_sdk/devices/subdevice.py
cognitive_sdk/devices/middlewares/__init__.py
cognitive_sdk/devices/middlewares/brainflow.py
cognitive_sdk/devices/middlewares/synthetic.py
cognitive_sdk/presets/Muse-2.json
cognitive_sdk/presets/Muse-S.json
cognitive_sdk/presets/OpenBCI-daisy.json
cognitive_sdk/presets/Synthetic.json
cognitive_sdk/presets/__init__.py
cognitive_sdk/utils/__init__.py
cognitive_sdk/utils/helpers.py
cognitive_sdk/utils/logger.py
cognitive_sdk/utils/ports.py
cognitive_sdk/utils/shared_state.py
cognitive_sdk-1.0.0.post1.dist-info/METADATA
cognitive_sdk-1.0.0.post1.dist-info/WHEEL
cognitive_sdk-1.0.0.post1.dist-info/top_level.txt
cognitive_sdk-1.0.0.post1.dist-info/RECORD
